setup.py
TracLineDiffMacro.egg-info/PKG-INFO
TracLineDiffMacro.egg-info/SOURCES.txt
TracLineDiffMacro.egg-info/entry_points.txt
TracLineDiffMacro.egg-info/top_level.txt
linediff/__init__.py
linediff/macro.py
