Metadata-Version: 1.0
Name: TracLineDiffMacro
Version: 0.1
Summary: A small macro to diff two lines of text.
Home-page: http://trac-hacks.org/wiki/
Author: Noah Kantrowitz
Author-email: coderanger@yahoo.com
License: BSD
Keywords: trac plugin macro diff
Platform: UNKNOWN
